Metadata-Version: 2.2
Name: datdeptrai
Version: 1.0.0
Requires-Dist: click
Dynamic: requires-dist
